{"_id":3373,"body":"<div><p><strong>Nếu muốn có được một mối quan hệ dài lâu và bền vững, hãy chú ý những nguyên tắc này.</strong></p><p><br /></p><p>Không phải ai cũng học được dễ dàng cách duy trì một mối quan hệ yêu đương thật đúng, thật lâu, thật bền. Có những người trải qua nhiều mối tình rồi, mới biết được hết bí quyết. Cái gì cũng vậy - muốn cho kết quả tốt, chúng ta cần rất nhiều sự nỗ lực. Tình yêu lại càng cần sự nỗ lực gấp đôi của cả 2 người.</p><p><br /></p><p>Nếu bạn đang hoang mang trong tình yêu, thì hãy xem bộ tranh dưới đây. Nó sẽ hướng dẫn bạn cái gì \"Không nên\" và cái gì \"Nên\" trong một mối quan hệ, từ đó, giúp bạn có được một mối quan hệ thật vui vẻ và dài lâu.</p><p><br /></p><p><img src=\"http://kenh14cdn.com/2016/5834855-13-1470403367-0-1470658622-1470680899-650-6898a2519a-1-1470807444-1470888568707.jpg\" /></p><p><em>Chỉ cần sở thích của họ không đi ngược các nguyên tắc đạo lý, không gây ảnh hưởng xấu đến những người xung quanh, thì chúng ta không có lý do gì cấm cản họ được tự do đam mê với sở thích của mình.</em></p><p><br /></p><p><img src=\"http://kenh14cdn.com/2016/5835005-5-1470403014-0-1470658284-1470680173-650-6898a2519a-1-1470807444-1470888568720.jpg\" /></p><p><em>Yêu, là thoải mái chia sẻ mọi thứ với nhau, không cần giấu diếm bất kỳ điều gì kinh khủng.</em></p><p><br /></p><p><img src=\"http://kenh14cdn.com/2016/5834955-4-1470403473-0-1470658208-1470680100-650-6898a2519a-1-1470807444-1470888568717.jpg\" /></p><p><em>Bạn học cách phát triển bản thân, cũng là học cách giúp mối quan hệ được tốt đẹp. 2 cá thể hoàn thiện sẽ làm cho tình yêu hoàn thiện.</em></p><p><br /></p><p><img src=\"http://kenh14cdn.com/2016/5835055-3-1470402998-0-1470658177-1470765277-650-6898a2519a-1-1470807444-1470888568723.jpg\" /></p><p><em>Đừng đánh mất sự kiểm soát mỗi khi cảm thấy không tin tưởng họ, hoặc cảm thấy bất an. Hãy kiềm chế, để tránh những lời nói không hay.</em></p><p><br /></p><p><img src=\"http://kenh14cdn.com/2016/5834905-2-1470403406-0-1470658108-1470679930-650-6898a2519a-1-1470807444-1470888568714.jpg\" /></p><p><em>Yêu là để người đó được tự do - ai đó đã nói như vậy. Và nó cũng có phần đúng. Chẳng ai có thể thoải mái yêu đương khi bị \"giam cầm\" trong không khí ngột ngạt cả.</em></p><p><br /></p><p><img src=\"http://kenh14cdn.com/2016/5835105-6-1470403064-0-1470658349-1470680286-650-6898a2519a-1-1470807444-1470888568726.jpg\" /></p><p><em>Cho đi chỉ để nhận về là biểu hiện của một tình yêu ích kỷ, và điều đó chắc chắn sẽ không khiến mối quan hệ của bạn dài lâu.</em></p><p><br /></p><p><img src=\"http://kenh14cdn.com/2016/5835155-9-1470403225-0-1470658443-1470680603-650-6898a2519a-1-1470807444-1470888568728.jpg\" /></p><p><em>Chẳng ai biết trước được tương lai sẽ thế nào. Thế nên tốt nhất, chúng ta hãy cứ tin tưởng vào bản thân mình trước tiên.</em></p><p><br /></p><p><img src=\"http://kenh14cdn.com/2016/5835255-7-1470403158-0-1470658376-1470680375-650-6898a2519a-1-1470807444-1470888568736.jpg\" /></p><p><em>Đừng bắt họ sống theo cách bạn muốn, nếu bạn không muốn yêu một manocanh.</em></p><p><br /></p><p><img src=\"http://kenh14cdn.com/2016/5835205-8-1470403193-0-1470658415-1470680501-650-6898a2519a-1-1470807444-1470888568733.jpg\" /></p><p><em>Bạn luôn đạt được cái bạn muốn sau mỗi lần tranh cãi? Bạn thấy hạnh phúc vì điều đó? Nếu đúng như vậy, thì bạn chỉ đang yêu bản thân mình hơn là yêu mối quan hệ này.</em></p><p><br /></p><p><img src=\"http://kenh14cdn.com/2016/5835355-11-1470403438-0-1470658527-1470680763-650-6898a2519a-1-1470807444-1470888568742.jpg\" /></p><p><em>Các cô gái thường xuyên bắt đối phương phải đoán xem họ đang nghĩ gì, cần gì... Điều này vô thức sẽ gây mệt mỏi cho các chàng trai. Hãy thẳng thắn nói ra.</em></p><p><br /></p><p><img src=\"http://kenh14cdn.com/2016/5835305-12-1470403336-0-1470658561-1470680846-650-6898a2519a-1-1470807444-1470888568739.jpg\" /></p><p><em>Tình yêu không phải lúc nào cũng kè kè cạnh bên 24/24. Mỗi người còn có những sở thích, công việc riêng. Hãy tạo cho mình một khoảng không gian riêng tư.</em></p><p><br /></p><p><img src=\"http://kenh14cdn.com/2016/5835405-10-1470403261-0-1470658507-1470680694-650-6898a2519a-1-1470807444-1470888568744.jpg\" /></p><p><em>Hãy luôn giữ bản thân được độc lập và sống đúng với cảm xúc của mình. Bất kỳ sự phụ thuộc nào cũng mang lại hệ quả không tốt.</em></p><p><br /></p><p><img src=\"http://kenh14cdn.com/2016/5835455-1-1470402868-0-1470658058-1470679854-650-6898a2519a-1-1470807444-1470888568746.jpg\" /></p><p><em>Không được là chính mình trong mối quan hệ chính là điều tồi tệ nhất.</em></p><p><br /></p><p><em>(Nguồn: Brightside - Dịch: Kenh14)</em></p></div>","cat_id":{"_id":14,"name":"Chuyện trò - Tâm sự"},"created_at":"2016-08-12T02:46:43.497Z","creator_id":631,"down_point":0,"tags":[],"title":"Những điều NÊN và KHÔNG NÊN trong tình yêu","up_point":10}