{"_id":11338,"title":"Một bài thơ viết dở","body":"<pre style=\"text-align: center;\"><em>Có thể sau này anh chẳng viết tặng em\nMà lời thương nhớ gắn liền tên người khác\nCô gái sau em.. Em thành điều rơi lạc\nCô gái giờ đây, trong bài hát của anh..</em>\n<em>\nCó thể với anh, qua rồi những ngày xanh\nVà sắp đến rồi, những ngày xanh khác\nRồi bản tình ca, những bổng trầm điệu nhạc\nSẽ chỉ còn trong trí tưởng nơi em.</em>\n<em>\nẤy mà hôm nay, em nghe một giai điệu quen\nCó gió thổi và có mùi hương cũ\nCó mùa Hạ cùng nhành hoa đã rũ\nBất chợt lắng nghe, và dừng lại.. Nhớ anh.</em>\n\n<figure class=\"aligncenter\"><img src=\"https://s3-ap-southeast-1.amazonaws.com/img.spiderum.com/sp-images/9f1afcf0f47011e791116f29996f4e29.jpg\" class=\"fr-fic fr-dib img-focus\"><figcaption class=\"image-description\" contenteditable=\"false\" placeholder=\"Chú thích ảnh (không bắt buộc)\">(còn đây là giấc mơ của em, cho tuổi xanh.)</figcaption></figure></pre>","cat_id":{"_id":31,"name":"Sáng tác"},"creator_id":15009,"created_at":"2018-01-08T12:36:17.512Z","down_point":2,"up_point":16,"tags":[]}