{"_id":4897,"body":"<p><img class=\"fr-dib fr-draggable\" src=\"https://s3-ap-southeast-1.amazonaws.com/img.spiderum.com/sp-images/1944fa2094d311e690d99737a5369f34.jpg\"></p><p><br></p><p>Pixar Animation Studios vốn nổi tiếng với những bộ phim hơi có phần \"so deep\", những sự lựa chọn cách kể câu chuyện một cách táo bạo. Trong Borrowed Time thì có vẻ hơi hướng nhiều hơn tới người lớn nhưng nó vẫn mang đậm chất Pixar với một nhân vật đang chất chứa cảm xúc và một sự tập trung rất lớn vào yếu tố background xung quanh nhân vật. Ngay từ những thước quay close-up đầu tiên bạn đã nhận rõ nhân vật được xây dựng một cách rất chi tiết. Bạn nhìn thấy cả những vết rách, vệt ố trên áo của nhân vật. Khi nhân vật lê bước dần tới vách đá thì chi tiết cát và những hòn đá lớn cùng càng được mô tả đậm nét hơn. Kể cả những chuyển động vật lý như bụi bay,... tất cả đều rất thật.</p><p>Borrowed Time nói về tình yêu sự khăng khít, gắn bó trong gia đình thế nhưng cảm xúc tập trung trong bộ phim là sự thất vọng và cảm giác tội lỗi. Mặc dù chỉ là một bộ phim ngắn nhưng thật sự đã để lại một cảm xúc khá mạnh mẽ và \"ám ảnh\" cho người xem.</p><p>Hai đạo diễn của bộ phim là Lou Hamou-Lhadj - là người tập trung phát triển tuyến các nhân vật trong Inside Out, Brave và Cars 2 và Andrew Coats- họa sĩ cho Brave , The Good Dinosaur và một số phim ngắn khác.</p><p>Dưới đây là link VIMEO của bộ phim.&nbsp;</p><p><a href=\"https://vimeo.com/187257744\" target=\"_blank\">https://vimeo.com/187257744</a></p>","cat_id":{"_id":22,"name":"Phim"},"created_at":"2016-10-18T01:41:14.858Z","creator_id":2539,"down_point":1,"tags":[],"title":"\"Borrowed Time\"- bộ phim ngắn khá u tối của Pixar","up_point":18}