{"_id":1676,"body":"<div>https://www.facebook.com/baodientuvtv/videos/556296524550959/<br/><br/>Đầu tiên là các bác xem link trên<br/>Tiếp theo là cho tôi thấy các bác nghĩ gì.<br/>Chứ cá nhân tôi thấy đây là 1 chứng minh rõ nhất cho sự dân trí thấp và thiếu hiểu biết + tích cực phá hoại của người dân Việt.<br/><br/>Người Việt sẽ không bao giờ phát triển nổi nếu còn tồn tại những vấn đề như thế này!</div>","cat_id":{"_id":6,"name":"Tranh luận"},"created_at":"2016-04-17T03:34:10.165Z","creator_id":531,"down_point":0,"tags":[],"title":"Lễ hội Carnaval ngày 10/3 âm lịch","top_point":0.9013137,"up_point":16}