{"_id":2698,"body":"<div>Làm sao để phá máy tính đứa bạn ghét mà không để lại dấu tích:<br/>Trong đời, sẽ có những đứa mà bạn bực mình vô cùng. Nó có thể đã cướp bồ bạn, cây bút của bạn, chỗ ngồi của bạn hay chỉ đơn giản là tại vì nó thở. Tuy nhiên, bạn không thể giết nó (sẽ bị công an bắt), xé bài của nó (cô sẽ hạ hạnh kiểm), đánh em nó (bố mẹ nó sẽ mách mẹ bạn). Cho nên, bạn hẳn nên tìm một cách khác để trả thù nó mà vẫn (nếu làm khéo) là người tử tế và lịch thiệp. Hãy tìm cách tiếp cận laptop của nó (cẩn thận camera hay người xung quanh) và làm theo các bước sau đây:<br/>1. Mua kim tiêm sạch ở nhà thuốc<br/>2. Hòa muối vào nước (50ml nước với 4 muỗng cà phê muối)<br/>3. Tìm bất kỳ cái lỗ nào trên CPU, hay laptop (tốt nhất là lỗ thoát khí là cái thứ dễ nhìn nhất)<br/>4. Dùng kim tiêm bơm nước muối vào lỗ, canh thời gian tầm 4-5 tiếng. Thù sẽ được trả.<br/>5. Hiệu quả sẽ tăng cao đặc biệt vào các thời điểm cận deadline, đối tượng có việc gấp, laptop mới được mua/thưởng.<br/>Chúc các bạn làm người lịch thiệp vui vẻ!<br/><br/><br/>Nguồn: Blooks</div>","cat_id":{"_id":7,"name":"Nghĩ gì xả nấy"},"created_at":"2016-05-30T12:58:28.454Z","creator_id":629,"down_point":0,"tags":[],"title":"Ghét một đứa thì nên làm gì?","top_point":0.8589313,"up_point":10}